CHANGES.rst
CONTRIBUTORS.rst
MANIFEST.in
README.rst
setup.py
docs/LICENSE.rst
src/collective/__init__.py
src/collective.tinymceplugins.codemagic.egg-info/PKG-INFO
src/collective.tinymceplugins.codemagic.egg-info/SOURCES.txt
src/collective.tinymceplugins.codemagic.egg-info/dependency_links.txt
src/collective.tinymceplugins.codemagic.egg-info/entry_points.txt
src/collective.tinymceplugins.codemagic.egg-info/namespace_packages.txt
src/collective.tinymceplugins.codemagic.egg-info/not-zip-safe
src/collective.tinymceplugins.codemagic.egg-info/requires.txt
src/collective.tinymceplugins.codemagic.egg-info/top_level.txt
src/collective/tinymceplugins/__init__.py
src/collective/tinymceplugins/codemagic/__init__.py
src/collective/tinymceplugins/codemagic/configure.zcml
src/collective/tinymceplugins/codemagic/skins.zcml
src/collective/tinymceplugins/codemagic/testing.py
src/collective/tinymceplugins/codemagic/profiles/default/metadata.xml
src/collective/tinymceplugins/codemagic/profiles/default/skins.xml
src/collective/tinymceplugins/codemagic/profiles/default/tinymce.xml
src/collective/tinymceplugins/codemagic/skins/tinymce_codemagic_plugins/tinymce_codemagic/codemagic.htm.pt
src/collective/tinymceplugins/codemagic/skins/tinymce_codemagic_plugins/tinymce_codemagic/editor_plugin.js
src/collective/tinymceplugins/codemagic/skins/tinymce_codemagic_plugins/tinymce_codemagic/editor_plugin_min.js
src/collective/tinymceplugins/codemagic/skins/tinymce_codemagic_plugins/tinymce_codemagic/editor_plugin_src.js
src/collective/tinymceplugins/codemagic/skins/tinymce_codemagic_plugins/tinymce_codemagic/css/codemirror.css
src/collective/tinymceplugins/codemagic/skins/tinymce_codemagic_plugins/tinymce_codemagic/css/default.css
src/collective/tinymceplugins/codemagic/skins/tinymce_codemagic_plugins/tinymce_codemagic/css/style.css
src/collective/tinymceplugins/codemagic/skins/tinymce_codemagic_plugins/tinymce_codemagic/img/code.png
src/collective/tinymceplugins/codemagic/skins/tinymce_codemagic_plugins/tinymce_codemagic/img/icons/file.png
src/collective/tinymceplugins/codemagic/skins/tinymce_codemagic_plugins/tinymce_codemagic/img/icons/lens.png
src/collective/tinymceplugins/codemagic/skins/tinymce_codemagic_plugins/tinymce_codemagic/img/icons/redo.png
src/collective/tinymceplugins/codemagic/skins/tinymce_codemagic_plugins/tinymce_codemagic/img/icons/undo.png
src/collective/tinymceplugins/codemagic/skins/tinymce_codemagic_plugins/tinymce_codemagic/js/beautify-html.js
