Metadata-Version: 1.0
Name: collective.tinymceplugins.codemagic
Version: 1.1
Summary: Integration of the CodeMagic TinyMCE plugin with Plone
Home-page: http://github.com/collective/collective.tinymceplugins.codemagic
Author: UNKNOWN
Author-email: UNKNOWN
License: gpl
Platform: UNKNOWN
Classifier: Programming Language :: Python
